[{"proportion_e10s_disabled":0.2969929159,"proportion_wau_crashes_2":0.0203257683,"proportion_wau_crashes_1":0.0646369797,"crash_rate_main_avg_by_user_and_e10s_disabled":8.6170345019,"crash_rate_content_avg_by_user_and_e10s_disabled":3.1638415525,"crash_rate_content_avg_by_user_and_e10s_enabled":52.5184036369,"proportion_new_profiles":0.0600246436,"proportion_new_crashes_1":0.040151075,"proportion_new_crashes_2":0.0129741844,"median_hours_between_crashes":27.54875,"date":"2016-11-21","proportion_e10s_enabled":0.7091430466,"crash_rate_main_avg_by_user_and_e10s_enabled":6.990816833,"proportion_multiple_crashes":0.8959738528,"crash_rate_plugin_avg_by_user_and_e10s_enabled":24.220466829,"crash_rate_main_avg_by_user":7.0986655775,"crash_rate_plugin_avg_by_user_and_e10s_disabled":17.4723853222,"proportion_new_crashes_bis":0.047429439,"crash_rate_plugin_avg_by_user":19.1573610906,"proportion_first_time_crashes":0.1040261472,"geom_hours_between_crashes":23.1534539383,"crash_rate_content_avg_by_user":16.4247559501}]
