[{"crash_rate_content_avg_by_user_and_e10s_disabled":3.0713177135,"proportion_new_crashes":0.0387022263,"crash_rate_content_avg_by_user_and_e10s_enabled":48.7178885606,"crash_rate_content_avg_by_user":11.7411763884,"proportion_e10s_enabled":0.6467821498,"prop_last_crash_content_mult":0.7773499366,"prop_last_crash_plugin_first":0,"prop_last_crash_main_mult":0.2226500634,"crash_rate_main_avg_by_user":6.71610116,"prop_last_crash_plugin_mult":0,"proportion_first_time_crashes":0.1085235746,"proportion_e10s_disabled":0.3579124787,"crash_rate_main_avg_by_user_and_e10s_enabled":9.1543669456,"median_hours_between_crashes":27.1976388889,"date":"2016-10-10","proportion_new_profiles":0.0618051502,"prop_last_crash_content_first":0.6380712311,"prop_last_crash_content_tot":0.762235047,"proportion_multiple_crashes":0.8914852499,"proportion_wau_crashes":0.0573679327,"prop_last_crash_main_first":0.3619287689,"crash_rate_plugin_avg_by_user_and_e10s_enabled":22.9556023642,"prop_last_crash_main_tot":0.237764953,"crash_rate_plugin_avg_by_user_and_e10s_disabled":17.2225385169,"crash_rate_plugin_avg_by_user":18.0046709221,"prop_last_crash_plugin_tot":0,"crash_rate_main_avg_by_user_and_e10s_disabled":7.7140165924,"geom_hours_between_crashes":23.063881708}]
