[{"crash_rate_content_avg_by_user_and_e10s_disabled":3.1839463136,"proportion_new_crashes":0.0351032377,"crash_rate_content_avg_by_user_and_e10s_enabled":51.8970946491,"crash_rate_content_avg_by_user":16.4678226761,"proportion_e10s_enabled":0.6219848083,"prop_last_crash_content_mult":0.5884716572,"prop_last_crash_plugin_first":0.1876440092,"prop_last_crash_main_mult":0.1332995882,"crash_rate_main_avg_by_user":7.2347484312,"prop_last_crash_plugin_mult":0.2782287546,"proportion_first_time_crashes":0.0798569383,"proportion_e10s_disabled":0.3849210228,"crash_rate_main_avg_by_user_and_e10s_enabled":6.4865792245,"median_hours_between_crashes":22.9625,"date":"2016-11-25","proportion_new_profiles":0.0417816115,"prop_last_crash_content_first":0.5909418203,"prop_last_crash_content_tot":0.5886689169,"proportion_multiple_crashes":0.9201430617,"proportion_wau_crashes":0.0880462611,"prop_last_crash_main_first":0.2214141705,"crash_rate_plugin_avg_by_user_and_e10s_enabled":19.6979098254,"prop_last_crash_main_tot":0.1403361489,"crash_rate_plugin_avg_by_user_and_e10s_disabled":24.8994503878,"crash_rate_plugin_avg_by_user":23.0737820977,"prop_last_crash_plugin_tot":0.2709949342,"crash_rate_main_avg_by_user_and_e10s_disabled":8.9884543765,"geom_hours_between_crashes":18.5161026283}]
