[{"proportion_e10s_disabled":0.3642030905,"proportion_wau_crashes_2":0.0179561407,"proportion_wau_crashes_1":0.0574055141,"crash_rate_main_avg_by_user_and_e10s_disabled":8.7302316283,"crash_rate_content_avg_by_user_and_e10s_disabled":3.1255012136,"crash_rate_content_avg_by_user_and_e10s_enabled":57.0274241555,"proportion_new_profiles":0.0458970391,"proportion_new_crashes_1":0.0265831732,"proportion_new_crashes_2":0.0075099949,"median_hours_between_crashes":28.9583333333,"date":"2016-09-30","proportion_e10s_enabled":0.6449094923,"crash_rate_main_avg_by_user_and_e10s_enabled":8.0767976262,"proportion_multiple_crashes":0.8854834437,"crash_rate_plugin_avg_by_user_and_e10s_enabled":32.7133679865,"crash_rate_main_avg_by_user":7.3666397995,"crash_rate_plugin_avg_by_user_and_e10s_disabled":19.2695256151,"proportion_new_crashes_bis":0.0425375093,"crash_rate_plugin_avg_by_user":19.4110785338,"proportion_first_time_crashes":0.1145165563,"geom_hours_between_crashes":24.5462154449,"crash_rate_content_avg_by_user":10.755697666}]
