[{"proportion_e10s_disabled":0.3161508448,"proportion_wau_crashes_2":0.0196406693,"proportion_wau_crashes_1":0.0624694702,"crash_rate_main_avg_by_user_and_e10s_disabled":7.8702011158,"crash_rate_content_avg_by_user_and_e10s_disabled":3.0279601053,"crash_rate_content_avg_by_user_and_e10s_enabled":48.8874673423,"proportion_new_profiles":0.0429589279,"proportion_new_crashes_1":0.0257939744,"proportion_new_crashes_2":0.0075145047,"median_hours_between_crashes":28.3691666667,"date":"2016-11-14","proportion_e10s_enabled":0.6875025037,"crash_rate_main_avg_by_user_and_e10s_enabled":9.7127571682,"proportion_multiple_crashes":0.8941810811,"crash_rate_plugin_avg_by_user_and_e10s_enabled":21.1307856589,"crash_rate_main_avg_by_user":7.1140574314,"crash_rate_plugin_avg_by_user_and_e10s_disabled":14.5440925198,"proportion_new_crashes_bis":0.0513664238,"crash_rate_plugin_avg_by_user":16.1364676484,"proportion_first_time_crashes":0.1058189189,"geom_hours_between_crashes":23.9590964563,"crash_rate_content_avg_by_user":15.5296387017}]
