[{"proportion_e10s_disabled":0.1341405706,"proportion_wau_crashes_2":0.0324772528,"proportion_wau_crashes_1":0.0916445665,"crash_rate_main_avg_by_user_and_e10s_disabled":8.3878931452,"crash_rate_content_avg_by_user_and_e10s_disabled":3.9540015506,"crash_rate_content_avg_by_user_and_e10s_enabled":59.3065582503,"proportion_new_profiles":0.0416878825,"proportion_new_crashes_1":0.0356876232,"proportion_new_crashes_2":0.0118469202,"median_hours_between_crashes":22.7705555556,"date":"2017-02-24","proportion_e10s_enabled":0.8686819763,"crash_rate_main_avg_by_user_and_e10s_enabled":5.5126848165,"proportion_multiple_crashes":0.8733082811,"crash_rate_plugin_avg_by_user_and_e10s_enabled":24.455042233,"crash_rate_main_avg_by_user":6.1008883328,"crash_rate_plugin_avg_by_user_and_e10s_disabled":21.5942962492,"proportion_new_crashes_bis":0.0608258929,"crash_rate_plugin_avg_by_user":20.9835795333,"proportion_first_time_crashes":0.1266917189,"geom_hours_between_crashes":19.778903392,"crash_rate_content_avg_by_user":28.6607691541}]
