[{"crash_rate_content_avg_by_user_and_e10s_disabled":0.156526624,"proportion_new_crashes":0.0120673802,"crash_rate_content_avg_by_user_and_e10s_enabled":6.7403256479,"crash_rate_content_avg_by_user":3.4722079898,"proportion_e10s_enabled":0.6695361471,"prop_last_crash_content_mult":0.4861772797,"prop_last_crash_plugin_first":0,"prop_last_crash_main_mult":0.5138227203,"crash_rate_main_avg_by_user":5.1053585242,"prop_last_crash_plugin_mult":0,"proportion_first_time_crashes":0.1696893718,"proportion_e10s_disabled":0.3423875192,"crash_rate_main_avg_by_user_and_e10s_enabled":4.2452066362,"median_hours_between_crashes":48.6609722222,"date":"2017-03-28","proportion_new_profiles":0.0577479446,"prop_last_crash_content_first":0.3753078312,"prop_last_crash_content_tot":0.4673649609,"proportion_multiple_crashes":0.8303663463,"proportion_wau_crashes":0.0196496618,"prop_last_crash_main_first":0.6246921688,"crash_rate_plugin_avg_by_user_and_e10s_enabled":17.1685782528,"prop_last_crash_main_tot":0.5326350391,"crash_rate_plugin_avg_by_user_and_e10s_disabled":13.5781785114,"crash_rate_plugin_avg_by_user":14.0964927663,"prop_last_crash_plugin_tot":0,"crash_rate_main_avg_by_user_and_e10s_disabled":8.1894391508,"geom_hours_between_crashes":33.5843742619}]
