[{"crash_rate_content_avg_by_user_and_e10s_disabled":3.8776381661,"proportion_new_crashes":0.0488976495,"crash_rate_content_avg_by_user_and_e10s_enabled":65.8743580669,"crash_rate_content_avg_by_user":23.9176060445,"proportion_e10s_enabled":0.6223185003,"prop_last_crash_content_mult":0.6456757209,"prop_last_crash_plugin_first":0.1982437863,"prop_last_crash_main_mult":0.1043242791,"crash_rate_main_avg_by_user":7.328535275,"prop_last_crash_plugin_mult":0.25,"proportion_first_time_crashes":0.085744184,"proportion_e10s_disabled":0.3822628604,"crash_rate_main_avg_by_user_and_e10s_enabled":6.0694732344,"median_hours_between_crashes":17.94,"date":"2017-01-02","proportion_new_profiles":0.0350610553,"prop_last_crash_content_first":0.6082006251,"prop_last_crash_content_tot":0.6424624494,"proportion_multiple_crashes":0.914255816,"proportion_wau_crashes":0.0910178514,"prop_last_crash_main_first":0.1935555886,"crash_rate_plugin_avg_by_user_and_e10s_enabled":28.2899494492,"prop_last_crash_main_tot":0.1119753449,"crash_rate_plugin_avg_by_user_and_e10s_disabled":21.3023763961,"crash_rate_plugin_avg_by_user":22.3977302528,"prop_last_crash_plugin_tot":0.2455622057,"crash_rate_main_avg_by_user_and_e10s_disabled":9.2566716201,"geom_hours_between_crashes":14.8507804444}]
