[{"proportion_wau_crashes_2":0.0223211405,"crash_rate_content_avg_by_user_and_e10s_disabled":3.8337489623,"proportion_new_crashes":0.0506504199,"crash_rate_content_avg_by_user_and_e10s_enabled":61.3695379291,"crash_rate_content_avg_by_user":22.1249398623,"proportion_e10s_enabled":0.7422631642,"crash_rate_main_avg_by_user":7.5121955271,"proportion_new_crashes_bis":0.0124831957,"proportion_first_time_crashes":0.1045311452,"proportion_e10s_disabled":0.2610311194,"crash_rate_main_avg_by_user_and_e10s_enabled":6.026154276,"proportion_new_crashes_2":0.0165651243,"median_hours_between_crashes":25.0497222222,"date":"2016-12-30","proportion_new_profiles":0.0539219894,"proportion_multiple_crashes":0.8954688548,"proportion_wau_crashes":0.0688191265,"crash_rate_plugin_avg_by_user_and_e10s_enabled":26.7186436975,"crash_rate_plugin_avg_by_user_and_e10s_disabled":20.2296649614,"crash_rate_plugin_avg_by_user":21.2002375724,"geom_hours_between_crashes":21.0394841162,"crash_rate_main_avg_by_user_and_e10s_disabled":9.531099916}]
