[{"proportion_e10s_disabled":0.3175395976,"proportion_wau_crashes_2":0.0194794424,"proportion_wau_crashes_1":0.0623332193,"crash_rate_main_avg_by_user_and_e10s_disabled":7.8832120223,"crash_rate_content_avg_by_user_and_e10s_disabled":3.4502633929,"crash_rate_content_avg_by_user_and_e10s_enabled":44.7155998491,"proportion_new_profiles":0.0603347147,"proportion_new_crashes_1":0.040075296,"proportion_new_crashes_2":0.0125163059,"median_hours_between_crashes":28.475,"date":"2016-11-10","proportion_e10s_enabled":0.6862003932,"crash_rate_main_avg_by_user_and_e10s_enabled":7.4377664313,"proportion_multiple_crashes":0.8927309924,"crash_rate_plugin_avg_by_user_and_e10s_enabled":19.5142178405,"crash_rate_main_avg_by_user":6.6717909513,"crash_rate_plugin_avg_by_user_and_e10s_disabled":15.9423685362,"proportion_new_crashes_bis":0.0485372947,"crash_rate_plugin_avg_by_user":16.6295124579,"proportion_first_time_crashes":0.1072690076,"geom_hours_between_crashes":23.9528457397,"crash_rate_content_avg_by_user":13.884200638}]
