[{"days":0, "count":18674},{"days":1, "count":9370},{"days":2, "count":5772},{"days":3, "count":4464},{"days":4, "count":3689},{"days":5, "count":3009},{"days":6, "count":2880},{"days":7, "count":2784},{"days":8, "count":2234},{"days":9, "count":1875},{"days":10, "count":1690},{"days":11, "count":1620},{"days":12, "count":1450},{"days":13, "count":1405},{"days":14, "count":1525},{"days":15, "count":1254},{"days":16, "count":1089},{"days":17, "count":1007},{"days":18, "count":962},{"days":19, "count":877},{"days":20, "count":956},{"days":21, "count":959},{"days":22, "count":793},{"days":23, "count":701},{"days":24, "count":731},{"days":25, "count":660},{"days":26, "count":662},{"days":27, "count":676},{"days":28, "count":724},{"days":29, "count":606},{"days":30, "count":523},{"days":31, "count":502},{"days":32, "count":493},{"days":33, "count":497},{"days":34, "count":509},{"days":35, "count":547},{"days":36, "count":452},{"days":37, "count":453},{"days":38, "count":418},{"days":39, "count":414},{"days":40, "count":402},{"days":41, "count":367},{"days":42, "count":424},{"days":43, "count":390},{"days":44, "count":368},{"days":45, "count":342},{"days":46, "count":345},{"days":47, "count":315},{"days":48, "count":344},{"days":49, "count":352},{"days":50, "count":281},{"days":51, "count":260},{"days":52, "count":263},{"days":53, "count":259},{"days":54, "count":233},{"days":55, "count":275},{"days":56, "count":311},{"days":57, "count":254},{"days":58, "count":254},{"days":59, "count":221},{"days":60, "count":184},{"days":61, "count":213},{"days":62, "count":240},{"days":63, "count":250},{"days":64, "count":224},{"days":65, "count":187},{"days":66, "count":150},{"days":67, "count":174},{"days":68, "count":181},{"days":69, "count":195},{"days":70, "count":197},{"days":71, "count":190},{"days":72, "count":138},{"days":73, "count":150},{"days":74, "count":153},{"days":75, "count":154},{"days":76, "count":161},{"days":77, "count":172},{"days":78, "count":148},{"days":79, "count":142},{"days":80, "count":137},{"days":81, "count":136},{"days":82, "count":122},{"days":83, "count":135},{"days":84, "count":145},{"days":85, "count":125},{"days":86, "count":100},{"days":87, "count":113},{"days":88, "count":102},{"days":89, "count":100},{"days":90, "count":104},{"days":91, "count":136},{"days":92, "count":96},{"days":93, "count":109},{"days":94, "count":104},{"days":95, "count":109},{"days":96, "count":97},{"days":97, "count":105},{"days":98, "count":114},{"days":99, "count":95},{"days":100, "count":80},{"days":101, "count":100},{"days":102, "count":66},{"days":103, "count":81},{"days":104, "count":108},{"days":105, "count":98},{"days":106, "count":82},{"days":107, "count":95},{"days":108, "count":74},{"days":109, "count":67},{"days":110, "count":78},{"days":111, "count":75},{"days":112, "count":88},{"days":113, "count":77},{"days":114, "count":70},{"days":115, "count":77},{"days":116, "count":70},{"days":117, "count":65},{"days":118, "count":60},{"days":119, "count":83},{"days":120, "count":96},{"days":121, "count":50},{"days":122, "count":50},{"days":123, "count":54},{"days":124, "count":66},{"days":125, "count":57},{"days":126, "count":67},{"days":127, "count":56},{"days":128, "count":54},{"days":129, "count":57},{"days":130, "count":54},{"days":131, "count":42},{"days":132, "count":65},{"days":133, "count":65},{"days":134, "count":58},{"days":135, "count":54},{"days":136, "count":46},{"days":137, "count":51},{"days":138, "count":48},{"days":139, "count":62},{"days":140, "count":51},{"days":141, "count":57},{"days":142, "count":46},{"days":143, "count":48},{"days":144, "count":42},{"days":145, "count":43},{"days":146, "count":43},{"days":147, "count":60},{"days":148, "count":52},{"days":149, "count":58},{"days":150, "count":42},{"days":151, "count":45},{"days":152, "count":57},{"days":153, "count":54},{"days":154, "count":53},{"days":155, "count":54},{"days":156, "count":61},{"days":157, "count":44},{"days":158, "count":53},{"days":159, "count":51},{"days":160, "count":48},{"days":161, "count":54},{"days":162, "count":40},{"days":163, "count":49},{"days":164, "count":33},{"days":165, "count":31},{"days":166, "count":53},{"days":167, "count":43},{"days":168, "count":50},{"days":169, "count":35},{"days":170, "count":49},{"days":171, "count":34},{"days":172, "count":27},{"days":173, "count":44},{"days":174, "count":28},{"days":175, "count":42},{"days":176, "count":40},{"days":177, "count":38},{"days":178, "count":30},{"days":179, "count":14},{"days":180, "count":22},{"days":181, "count":14},{"days":182, "count":9},{"days":183, "count":3}]