[{"crash_rate_content_avg_by_user_and_e10s_disabled":2.9388449742,"proportion_new_crashes":0.033421757,"crash_rate_content_avg_by_user_and_e10s_enabled":53.4452129682,"crash_rate_content_avg_by_user":18.2134598613,"proportion_e10s_enabled":0.6404785744,"prop_last_crash_content_mult":0.5936296151,"prop_last_crash_plugin_first":0.1833567416,"prop_last_crash_main_mult":0.1276645183,"crash_rate_main_avg_by_user":7.2758425126,"prop_last_crash_plugin_mult":0.2787058665,"proportion_first_time_crashes":0.0800998999,"proportion_e10s_disabled":0.3637682953,"crash_rate_main_avg_by_user_and_e10s_enabled":7.3514289745,"median_hours_between_crashes":23.0636111111,"date":"2016-12-12","proportion_new_profiles":0.0422153047,"prop_last_crash_content_first":0.6081460674,"prop_last_crash_content_tot":0.5947923815,"proportion_multiple_crashes":0.9199001001,"proportion_wau_crashes":0.0896777607,"prop_last_crash_main_first":0.208497191,"crash_rate_plugin_avg_by_user_and_e10s_enabled":19.5699952439,"prop_last_crash_main_tot":0.1341392073,"crash_rate_plugin_avg_by_user_and_e10s_disabled":26.9708055203,"crash_rate_plugin_avg_by_user":23.7773944895,"prop_last_crash_plugin_tot":0.2710684112,"crash_rate_main_avg_by_user_and_e10s_disabled":8.2336851299,"geom_hours_between_crashes":18.6241030302}]
