[{"crash_rate_content_avg_by_user_and_e10s_disabled":3.6198413058,"proportion_new_crashes":0.0326083347,"crash_rate_content_avg_by_user_and_e10s_enabled":52.6040431398,"crash_rate_content_avg_by_user":13.3448177672,"proportion_e10s_enabled":0.5542091412,"prop_last_crash_content_mult":0.6134173879,"prop_last_crash_plugin_first":0.2150259067,"prop_last_crash_main_mult":0.1257971168,"crash_rate_main_avg_by_user":6.8589091144,"prop_last_crash_plugin_mult":0.2607854953,"proportion_first_time_crashes":0.0864030975,"proportion_e10s_disabled":0.4530506065,"crash_rate_main_avg_by_user_and_e10s_enabled":6.8100159079,"median_hours_between_crashes":21.23,"date":"2016-10-24","proportion_new_profiles":0.0452419464,"prop_last_crash_content_first":0.5350091024,"prop_last_crash_content_tot":0.6066426692,"proportion_multiple_crashes":0.9135969025,"proportion_wau_crashes":0.0827745589,"prop_last_crash_main_first":0.2499649909,"crash_rate_plugin_avg_by_user_and_e10s_enabled":26.4684943246,"prop_last_crash_main_tot":0.1365256057,"crash_rate_plugin_avg_by_user_and_e10s_disabled":18.7214072596,"crash_rate_plugin_avg_by_user":19.8130117978,"prop_last_crash_plugin_tot":0.2568317251,"crash_rate_main_avg_by_user_and_e10s_disabled":8.6339357771,"geom_hours_between_crashes":17.4419674985}]
